stroll/__init__.py
stroll/conllu.py
stroll/download.py
stroll/graph.py
stroll/labels.py
stroll/loss.py
stroll/model.py
stroll/naf.py
stroll/srl.py
stroll/stanza.py
stroll_srl-0.5.1.dist-info/LICENSE
stroll_srl-0.5.1.dist-info/METADATA
stroll_srl-0.5.1.dist-info/WHEEL
stroll_srl-0.5.1.dist-info/top_level.txt
stroll_srl-0.5.1.dist-info/RECORD
