Metadata-Version: 2.1
Name: stroll-srl
Version: 0.5.1
Summary: Graph based semantic role labeler
Home-page: https://github.com/Filter-Bubble/stroll
Author: Jisk Attema
Author-email: j.attema@esciencecenter.nl
License: UNKNOWN
Platform: UNKNOWN
Classifier: Programming Language :: Python :: 3
Classifier: Development Status :: 4 - Beta
Classifier: Environment :: Console
Classifier: License :: OSI Approved :: Apache Software License
Classifier: Operating System :: OS Independent
Requires-Python: >=3.6
Requires-Dist: torch
Requires-Dist: dgl
Requires-Dist: matplotlib
Requires-Dist: numpy
Requires-Dist: sklearn
Requires-Dist: progress
Requires-Dist: argparse
Requires-Dist: fasttext
Requires-Dist: seaborn
Requires-Dist: stanza
Requires-Dist: KafNafParserPy
